# ðŸ§  CPython Interpreter â€” Ichki Ishlash Mexanizmi (Advanced)

Ushbu bo'lim Pythonni "til sifatida emas, balki virtual mashina sifatida" tushunishga yordam beradi.

CPython â€” Pythonning standart implementatsiyasi bo'lib, quyidagilarni bajaradi:

- Python kodini AST â†’ Bytecode ga kompilyatsiya qiladi
- Bytecode'ni CPython Virtual Machine (CEval loop) orqali bajaradi
- Xotira boshqaruvi uchun Reference Counting + Garbage Collectordan foydalanadi
- Thread xavfsizligi uchun **GIL (Global Interpreter Lock)**ga ega

## ðŸ“Œ 1. Python â†’ Bytecode â†’ Interpreter Execution Pipeline

```
source.py
   â”‚
   â–¼
[Parser] â†’ AST
   â”‚
   â–¼
[Compiler] â†’ Bytecode (.pyc)
   â”‚
   â–¼
[CPython VM] â†’ Execution
```

## ðŸ§© 2. Bytecode â€” Pythonning Mashina Tiliga Eng Yaqin Qismi

Pythonning bytecode'i â€” bu stack-based virtual machine uchun ko'rsatmalar to'plami.

**Misol:**

```python
def add(a, b):
    return a + b
```

**Bytecode tahlili (dis bilan):**

```python
import dis

def add(a, b):
    return a + b

dis.dis(add)
```

**Natija:**

```
  2           0 LOAD_FAST                0 (a)
              2 LOAD_FAST                1 (b)
              4 BINARY_ADD
              6 RETURN_VALUE
```

**Tushuntirish:**

| Bytecode | Vazifasi |
|----------|----------|
| `LOAD_FAST` | Lokal o'zgaruvchilarni operand stack'ga yuklaydi |
| `BINARY_ADD` | Stackning ikki elementini olib, qo'shib, natijani qaytarib stack'ga qo'yadi |
| `RETURN_VALUE` | Stackdagi oxirgi qiymatni qaytaradi |

ðŸ“Œ **Python bytecode'i register-based emas, balki stack-based VM'da ishlaydi.**

## ðŸ” 3. dis moduli bilan chuqur tahlil

**Misol: if-else bytecode**

```python
def f(x):
    if x > 10:
        return "big"
    return "small"

dis.dis(f)
```

**Natija:**

```
  2           0 LOAD_FAST                0 (x)
              2 LOAD_CONST               1 (10)
              4 COMPARE_OP               4 (>)
              6 POP_JUMP_IF_FALSE       14

  3           8 LOAD_CONST               2 ('big')
             10 RETURN_VALUE

  4     >>   14 LOAD_CONST               3 ('small')
             16 RETURN_VALUE
```

**Muhim nuqtalar:**

- Conditional branching real jump pointerlar bilan boshqariladi
- CPython VM'da goto yo'q, lekin bytecode'da jump instructions bor

## ðŸ”¥ 4. CPython VM (CEval Loop) â€” Pythonning yuragi

CEval Loop â€” bytecode instruktsiyalarni ketma-ket o'qib bajaradigan "motor".

**Soddalashtirilgan pseudocode:**

```c
for (;;) {
    instruction = *next_instr++;
    switch(instruction) {

        case LOAD_FAST:
            push(fastlocals[arg]);
            continue;

        case BINARY_ADD:
            right = pop();
            left = pop();
            push(left + right);
            continue;

        case RETURN_VALUE:
            return pop();
    }
}
```

ðŸ”Ž **Muhim joy:** Har bir bytecode CPU instruction emas â€” CEval loop uni C kodida emulyatsiya qiladi.

Shu sababli Python C-ga nisbatan sekin.

## ðŸ§± 5. GIL (Global Interpreter Lock) â€” Real, Advanced Tushuntirish

GIL â€” bu bitta interpretator konteksti uchun bitta vaqtning o'zida faqat bitta thread bytecode bajarishi mumkin degan mexanizm.

### ðŸ”¥ Nima uchun GIL mavjud?

- CPython reference countingdan foydalanadi
- `PyObject.refcount++` â†’ thread-safe emas

**Mutaxassislar uchun eng muhim gap:**

GIL bo'lmasa, har bir refcount operatsiya atomic bo'lishi kerak bo'lardi â†’ bu Pythonni yanada sekinlashtirardi.

## ðŸ§¬ 6. GIL qanday ishlaydi? (Ichki mexanizm)

```
Thread A ----\
               â”€â”€â–º [ GIL Acquired ] â†’ Bytecode executes â†’ Release
Thread B ----/
```

**GIL every 5ms (yoki bytecode count) dan keyin:**

- interpreterni to'xtatadi
- "context switch" uchun boshqa threadga ruxsat beradi

ðŸ“Œ **CPU-bound kodda threading tezlikni oshirmaydi.**

## âš¡ 7. Threading vs Multiprocessing (Real CPython Concurrency Model)

### ðŸ§µ 1. Threading

- GIL mavjud
- Bir vaqtning o'zida bitta thread bytecode bajaradi
- I/O-bound vazifalar juda tez
- CPU-bound vazifalar sekin

```
Python Threads â†’ concurrent
CPU Execution â†’ sequential (GIL)
```

**ðŸ”¥ Qachon ishlatamiz?**

- HTTP request kutish
- File/DB/Redis I/O
- Sleep, network polling

### ðŸš€ 2. Multiprocessing

- Har bir process â†’ o'z GIL ga ega
- Haqiqiy parallelism
- CPU-bound vazifalar uchun ideal

```
Process A â†’ GIL A
Process B â†’ GIL B
Process C â†’ GIL C
```

**Kamchilik:**

- IPC (processlararo aloqa) sekin
- Ko'p xotira talab qiladi

## ðŸ§ª Benchmark: Thread vs Process (CPU-bound)

```python
import time
from threading import Thread
from multiprocessing import Process

def cpu_task():
    s = 0
    for i in range(50_000_000):
        s += i
    return s

# Threads
start = time.time()
t1 = Thread(target=cpu_task)
t2 = Thread(target=cpu_task)
t1.start(); t2.start()
t1.join(); t2.join()
print("Threads:", time.time() - start)

# Processes
start = time.time()
p1 = Process(target=cpu_task)
p2 = Process(target=cpu_task)
p1.start(); p2.start()
p1.join(); p2.join()
print("Processes:", time.time() - start)
```

ðŸ“Œ **Natija:** Processes threadsdan 2Ã—â€“3Ã— tez bo'ladi (CPU-bound vazifalarda).

## ðŸ“š Yakuniy xulosa (Advanced Level)

| Mavzu | Muhim xulosa |
|-------|--------------|
| Bytecode | Pythonni register emas, stack VM boshqaradi |
| dis moduli | Real execution flow'ni ko'rishning eng to'g'ri yo'li |
| GIL | Thread xavfsizligi uchun, lekin CPU parallelizmini bloklaydi |
| Threading | I/O uchun juda kuchli |
| Multiprocessing | CPU uchun yagona to'g'ri yo'l |

Pythonning performance optimizatsiyasi uchun bu bilim majburiy.
